bespokelang/__init__.py
bespokelang/__main__.py
bespokelang/cli.py
bespokelang/exceptions.py
bespokelang/interpreter.py
bespokelang-1.2.6.dist-info/METADATA
bespokelang-1.2.6.dist-info/WHEEL
bespokelang-1.2.6.dist-info/entry_points.txt
bespokelang-1.2.6.dist-info/top_level.txt
bespokelang-1.2.6.dist-info/RECORD
