Metadata-Version: 2.4
Name: bespokelang
Version: 1.2.6
Summary: Run programs written in the Bespoke esolang.
Author-email: Josiah Winslow <winslowjosiah@gmail.com>
Project-URL: Homepage, https://github.com/winslowjosiah/bespokelang
Project-URL: Issues, https://github.com/winslowjosiah/bespokelang/issues
Classifier: Programming Language :: Python :: 3
Classifier: License :: OSI Approved :: GNU General Public License v3 (GPLv3)
Classifier: Operating System :: OS Independent
Requires-Python: >=3.10
